numerosprimos/pythonprimos.py
numerosprimoscelx2-1.0.dist-info/LICENSE.txt
numerosprimoscelx2-1.0.dist-info/METADATA
numerosprimoscelx2-1.0.dist-info/WHEEL
numerosprimoscelx2-1.0.dist-info/top_level.txt
numerosprimoscelx2-1.0.dist-info/RECORD
