Metadata-Version: 2.1
Name: numerosprimoscelx2
Version: 1.0
Summary: Herramienta para averiguar los números primos hasta una cifra especificada.
Home-page: UNKNOWN
Author: Celeste Laura Clavijo
License: UNKNOWN
Keywords: numeros primos
Platform: UNKNOWN
Classifier: Development Status :: 4 - Beta
Classifier: Intended Audience :: Developers
Classifier: Topic :: Utilities
Classifier: License :: OSI Approved :: GNU General Public License v3 (GPLv3)
Classifier: Programming Language :: Python :: 3
Classifier: Operating System :: OS Independent
License-File: LICENSE.txt
